LICENSE
MANIFEST.in
README.md
requirements.txt
setup.cfg
setup.py
versioneer.py
opsdroid_homeassistant/__init__.py
opsdroid_homeassistant/_version.py
opsdroid_homeassistant.egg-info/PKG-INFO
opsdroid_homeassistant.egg-info/SOURCES.txt
opsdroid_homeassistant.egg-info/dependency_links.txt
opsdroid_homeassistant.egg-info/entry_points.txt
opsdroid_homeassistant.egg-info/not-zip-safe
opsdroid_homeassistant.egg-info/requires.txt
opsdroid_homeassistant.egg-info/top_level.txt
opsdroid_homeassistant/connector/__init__.py
opsdroid_homeassistant/matcher/__init__.py
opsdroid_homeassistant/skill/__init__.py
opsdroid_homeassistant/tests/conftest.py
opsdroid_homeassistant/tests/docker-compose.yml
opsdroid_homeassistant/tests/test_connector.py
opsdroid_homeassistant/tests/test_matcher.py
opsdroid_homeassistant/tests/test_skill.py
opsdroid_homeassistant/tests/hass_config/configuration.yaml
opsdroid_homeassistant/tests/hass_config/.storage/auth
opsdroid_homeassistant/tests/hass_config/.storage/auth_provider.homeassistant
opsdroid_homeassistant/tests/hass_config/.storage/core.area_registry
opsdroid_homeassistant/tests/hass_config/.storage/core.config
opsdroid_homeassistant/tests/hass_config/.storage/core.config_entries
opsdroid_homeassistant/tests/hass_config/.storage/core.device_registry
opsdroid_homeassistant/tests/hass_config/.storage/core.entity_registry
opsdroid_homeassistant/tests/hass_config/.storage/http
opsdroid_homeassistant/tests/hass_config/.storage/onboarding
opsdroid_homeassistant/tests/hass_config/.storage/person
opsdroid_homeassistant/tests/mock_skill/__init__.py