Metadata-Version: 2.1
Name: opsdroid-homeassistant
Version: 0.1.8
Summary: Home Assistant support for opsdroid
Home-page: https://github.com/opsdroid/opsdroid-homeassistant
Author: Jacob Tomlinson
Author-email: jacob@tomlinson.email
License: Apache Software License 2.0
Keywords: Opsdroid Home Assistant
Platform: UNKNOWN
Classifier: Development Status :: 2 - Pre-Alpha
Classifier: Intended Audience :: Developers
Classifier: License :: OSI Approved :: Apache Software License
Classifier: Natural Language :: English
Classifier: Programming Language :: Python :: 3
Classifier: Programming Language :: Python :: 3.6
Classifier: Programming Language :: Python :: 3.7
